ggd_py_utils/__init__.py
ggd_py_utils/formating/__init__.py
ggd_py_utils/formating/numeric.py
ggd_py_utils/machine_learning/__init__.py
ggd_py_utils/machine_learning/data/__init__.py
ggd_py_utils/machine_learning/data/cleaning.py
ggd_py_utils/machine_learning/data/corpus_metrics.py
ggd_py_utils/machine_learning/fasttext/__init__.py
ggd_py_utils/machine_learning/fasttext/supervised/__init__.py
ggd_py_utils/machine_learning/fasttext/supervised/data_preparation.py
ggd_py_utils/machine_learning/fasttext/supervised/predictions.py
ggd_py_utils/machine_learning/fasttext/supervised/training.py
ggd_py_utils/machine_learning/fasttext/unsupervised/__init__.py
ggd_py_utils/machine_learning/fasttext/unsupervised/data_preparation.py
ggd_py_utils/machine_learning/fasttext/unsupervised/embeddings.py
ggd_py_utils/machine_learning/fasttext/unsupervised/plots.py
ggd_py_utils/machine_learning/fasttext/unsupervised/predictions.py
ggd_py_utils/machine_learning/fasttext/unsupervised/semantic_search.py
ggd_py_utils/machine_learning/fasttext/unsupervised/training.py
ggd_py_utils/machine_learning/sbert/__init__.py
ggd_py_utils/machine_learning/sbert/embeddings.py
ggd_py_utils/machine_learning/sbert/plots.py
ggd_py_utils/machine_learning/sbert/semantic_search.py
ggd_py_utils/tracing/__init__.py
ggd_py_utils/tracing/file.py
ggd_py_utils/tracing/metrics.py
ggd_py_utils-1.0.0.dist-info/LICENSE
ggd_py_utils-1.0.0.dist-info/METADATA
ggd_py_utils-1.0.0.dist-info/WHEEL
ggd_py_utils-1.0.0.dist-info/top_level.txt
ggd_py_utils-1.0.0.dist-info/RECORD
