Metadata-Version: 2.1
Name: ggd-py-utils
Version: 1.0.0
Summary: A collection of utility functions for my projects.
Home-page: https://github.com/ggaldamesd/ggd-utils
Author: Gerardo Ignacio Galdames Díaz
Author-email: gerardogaldames@gmail.com
Classifier: Programming Language :: Python :: 3
Classifier: License :: OSI Approved :: MIT License
Classifier: Operating System :: OS Independent
Requires-Python: >=3.6
License-File: LICENSE
Requires-Dist: faiss-cpu ==1.8.0
Requires-Dist: unidecode ==1.3.8
Requires-Dist: colorama ==0.4.6
Requires-Dist: chime ==0.7.0
Requires-Dist: fasttext-wheel ==0.9.2
Requires-Dist: plotly ==5.22.0
Requires-Dist: nltk ==3.8.1
Requires-Dist: tf-keras ==2.18.0
Requires-Dist: torch ==2.2.2
Requires-Dist: numpy ==1.26.4
Requires-Dist: sentence-transformers ==3.0.1
